[
  {
    "id": "vyborg",
    "name": "Выборг",
    "list": [
      "ВЫБОРГ ЛЕНИНА 9"
    ]
  },
  {
    "id": "iskitim",
    "name": "Искитим",
    "list": [
      "КОМСОМОЛЬСКАЯ 40"
    ]
  },
  {
    "id": "omsk",
    "name": "Омск",
    "list": [
      "ВОКЗАЛЬНАЯ 16",
      "ХОЛОДИЛЬНАЯ 31"
    ]
  },
  {
    "id": "spb",
    "name": "Санкт-Петербург",
    "list": [
      "ЛЕСНОЙ ПРОСПЕКТ 77",
      "НАБЕРЕЖНАЯ РЕКИ КАРПОВКИ 20"
    ]
  },
  {
    "id": "novosibirsk",
    "name": "Новосибирск",
    "list": [
      "ВОСХОД 3",
      "БОЛЬШЕВИТСКАЯ 22",
      "ДИМИТРОВА 7",
      "КРАСНЫЙ ПРОСПЕКТ 50",
      "КРАСИНА 62",
      "ЛЕНИНГРАДСКАЯ 100"
    ]
  },
  {
    "id": "barnaul",
    "name": "Барнаул",
    "list": []
  }
]